tnorma/__init__.py
tnorma/tnorma.py
tnorma-0.0.3.dist-info/LICENSE
tnorma-0.0.3.dist-info/METADATA
tnorma-0.0.3.dist-info/WHEEL
tnorma-0.0.3.dist-info/top_level.txt
tnorma-0.0.3.dist-info/RECORD
