Metadata-Version: 2.1
Name: tnorma
Version: 0.0.3
Summary: Temporal normalization (from 0 to 100% with step interval)
Home-page: https://github.com/demotu/tnorma
Author: Marcos Duarte
Author-email: duartexyz@gmail.com
License: UNKNOWN
Platform: UNKNOWN
Classifier: Programming Language :: Python :: 3
Classifier: License :: OSI Approved :: MIT License
Classifier: Operating System :: OS Independent
Requires-Python: >=3.6
